{
  "visState": "{\"type\":\"table\",\"listeners\":{},\"params\":{\"perPage\":10,\"showPartialRows\":false,\"showMeticsAtAllLevels\":false},\"aggs\":[{\"type\":\"avg\",\"params\":{\"field\":\"fs.used\"},\"id\":\"1\",\"schema\":\"metric\"},{\"type\":\"avg\",\"params\":{\"field\":\"fs.used_p\"},\"id\":\"2\",\"schema\":\"metric\"},{\"type\":\"avg\",\"params\":{\"field\":\"fs.total\"},\"id\":\"3\",\"schema\":\"metric\"},{\"type\":\"avg\",\"params\":{\"field\":\"fs.free\"},\"id\":\"4\",\"schema\":\"metric\"},{\"type\":\"avg\",\"params\":{\"field\":\"fs.free\"},\"id\":\"5\",\"schema\":\"metric\"},{\"type\":\"terms\",\"params\":{\"orderBy\":\"1\",\"field\":\"fs.device_name\",\"order\":\"desc\",\"size\":5},\"id\":\"6\",\"schema\":\"bucket\"},{\"type\":\"terms\",\"params\":{\"orderBy\":\"1\",\"field\":\"fs.mount_point\",\"order\":\"desc\",\"size\":5},\"id\":\"7\",\"schema\":\"bucket\"}]}",
  "description": "",
  "title": "Disk-usage",
  "uiStateJSON": "{}",
  "version": 1,
  "kibanaSavedObjectMeta": {
    "searchSourceJSON": "{\"filter\":[]}"
  }
}