{
  "objects": [
    {
      "attributes": {
        "description": "Includes Visual Builder Metric Interval size 90 days",
        "hits": 0,
        "kibanaSavedObjectMeta": {
          "searchSourceJSON": "{\"query\":{\"language\":\"kuery\",\"query\":\"\"},\"filter\":[]}"
        },
        "optionsJSON": "{\"hidePanelTitles\":false,\"useMargins\":true}",
        "panelsJSON": "[{\"embeddableConfig\":{},\"gridData\":{\"x\":0,\"y\":0,\"w\":17,\"h\":19,\"i\":\"1\"},\"panelIndex\":\"1\",\"title\":\"\",\"version\":\"7.3.0\",\"panelRefName\":\"panel_0\"},{\"embeddableConfig\":{\"vis\":{\"legendOpen\":false}},\"gridData\":{\"x\":17,\"y\":0,\"w\":18,\"h\":19,\"i\":\"2\"},\"panelIndex\":\"2\",\"title\":\"User Management Actions\",\"version\":\"7.3.0\",\"panelRefName\":\"panel_1\"},{\"embeddableConfig\":{},\"gridData\":{\"x\":0,\"y\":46,\"w\":9,\"h\":16,\"i\":\"3\"},\"panelIndex\":\"3\",\"title\":\"Created Users\",\"version\":\"7.3.0\",\"panelRefName\":\"panel_2\"},{\"embeddableConfig\":{},\"gridData\":{\"x\":35,\"y\":0,\"w\":13,\"h\":19,\"i\":\"4\"},\"panelIndex\":\"4\",\"title\":\"Event Codes\",\"version\":\"7.3.0\",\"panelRefName\":\"panel_3\"},{\"embeddableConfig\":{},\"gridData\":{\"x\":9,\"y\":46,\"w\":9,\"h\":16,\"i\":\"5\"},\"panelIndex\":\"5\",\"title\":\"Enabled Users\",\"version\":\"7.3.0\",\"panelRefName\":\"panel_4\"},{\"embeddableConfig\":{},\"gridData\":{\"x\":0,\"y\":69,\"w\":9,\"h\":16,\"i\":\"6\"},\"panelIndex\":\"6\",\"title\":\"Disabled Users\",\"version\":\"7.3.0\",\"panelRefName\":\"panel_5\"},{\"embeddableConfig\":{},\"gridData\":{\"x\":18,\"y\":46,\"w\":9,\"h\":16,\"i\":\"7\"},\"panelIndex\":\"7\",\"title\":\"Deleted Users\",\"version\":\"7.3.0\",\"panelRefName\":\"panel_6\"},{\"embeddableConfig\":{\"vis\":{\"defaultColors\":{\"0 - 4\":\"rgb(247,252,245)\",\"12 - 16\":\"rgb(35,139,69)\",\"4 - 8\":\"rgb(199,233,192)\",\"8 - 12\":\"rgb(116,196,118)\"},\"legendOpen\":false}},\"gridData\":{\"x\":0,\"y\":19,\"w\":27,\"h\":20,\"i\":\"8\"},\"panelIndex\":\"8\",\"title\":\"Actions performed over Users\",\"version\":\"7.3.0\",\"panelRefName\":\"panel_7\"},{\"embeddableConfig\":{},\"gridData\":{\"x\":18,\"y\":69,\"w\":9,\"h\":16,\"i\":\"9\"},\"panelIndex\":\"9\",\"title\":\"Passwords Changes\",\"version\":\"7.3.0\",\"panelRefName\":\"panel_8\"},{\"embeddableConfig\":{},\"gridData\":{\"x\":9,\"y\":69,\"w\":9,\"h\":16,\"i\":\"15\"},\"panelIndex\":\"15\",\"title\":\"Unlocked Users\",\"version\":\"7.3.0\",\"panelRefName\":\"panel_9\"},{\"embeddableConfig\":{},\"gridData\":{\"x\":36,\"y\":69,\"w\":12,\"h\":16,\"i\":\"16\"},\"panelIndex\":\"16\",\"title\":\"Users Changes\",\"version\":\"7.3.0\",\"panelRefName\":\"panel_10\"},{\"embeddableConfig\":{},\"gridData\":{\"x\":27,\"y\":69,\"w\":9,\"h\":16,\"i\":\"20\"},\"panelIndex\":\"20\",\"title\":\"Locked-out Users\",\"version\":\"7.3.0\",\"panelRefName\":\"panel_11\"},{\"embeddableConfig\":{},\"gridData\":{\"x\":27,\"y\":19,\"w\":21,\"h\":20,\"i\":\"21\"},\"panelIndex\":\"21\",\"title\":\"User Management Actions Distributions over Time\",\"version\":\"7.3.0\",\"panelRefName\":\"panel_12\"},{\"embeddableConfig\":{},\"gridData\":{\"x\":27,\"y\":39,\"w\":21,\"h\":23,\"i\":\"22\"},\"panelIndex\":\"22\",\"version\":\"7.3.1\",\"panelRefName\":\"panel_13\"},{\"embeddableConfig\":{},\"gridData\":{\"x\":0,\"y\":85,\"w\":48,\"h\":19,\"i\":\"23\"},\"panelIndex\":\"23\",\"version\":\"7.3.1\",\"panelRefName\":\"panel_14\"},{\"gridData\":{\"x\":0,\"y\":62,\"w\":9,\"h\":7,\"i\":\"24\"},\"version\":\"7.3.1\",\"panelIndex\":\"24\",\"embeddableConfig\":{},\"title\":\"\",\"panelRefName\":\"panel_15\"},{\"gridData\":{\"x\":9,\"y\":39,\"w\":9,\"h\":7,\"i\":\"25\"},\"version\":\"7.3.1\",\"panelIndex\":\"25\",\"embeddableConfig\":{},\"title\":\"\",\"panelRefName\":\"panel_16\"},{\"gridData\":{\"x\":18,\"y\":39,\"w\":9,\"h\":7,\"i\":\"26\"},\"version\":\"7.3.1\",\"panelIndex\":\"26\",\"embeddableConfig\":{},\"title\":\"\",\"panelRefName\":\"panel_17\"},{\"gridData\":{\"x\":0,\"y\":39,\"w\":9,\"h\":7,\"i\":\"27\"},\"version\":\"7.3.1\",\"panelIndex\":\"27\",\"embeddableConfig\":{},\"title\":\"\",\"panelRefName\":\"panel_18\"},{\"gridData\":{\"x\":9,\"y\":62,\"w\":9,\"h\":7,\"i\":\"28\"},\"version\":\"7.3.1\",\"panelIndex\":\"28\",\"embeddableConfig\":{},\"title\":\"\",\"panelRefName\":\"panel_19\"},{\"gridData\":{\"x\":18,\"y\":62,\"w\":9,\"h\":7,\"i\":\"29\"},\"version\":\"7.3.1\",\"panelIndex\":\"29\",\"embeddableConfig\":{},\"title\":\"\",\"panelRefName\":\"panel_20\"},{\"gridData\":{\"x\":27,\"y\":62,\"w\":9,\"h\":7,\"i\":\"30\"},\"version\":\"7.3.1\",\"panelIndex\":\"30\",\"embeddableConfig\":{},\"title\":\"\",\"panelRefName\":\"panel_21\"},{\"gridData\":{\"x\":36,\"y\":62,\"w\":12,\"h\":7,\"i\":\"31\"},\"version\":\"7.3.1\",\"panelIndex\":\"31\",\"embeddableConfig\":{},\"title\":\"\",\"panelRefName\":\"panel_22\"}]",
        "timeRestore": false,
        "title": "[winlogbeat] User Management Events",
        "version": 1
      },
      "id": "71f720f0-ff18-11e9-8405-516218e3d268",
      "migrationVersion": {
        "dashboard": "7.3.0"
      },
      "references": [
        {
          "id": "2dc6b820-b9e8-11e9-b6a2-c9b4015c4baf",
          "name": "panel_0",
          "type": "visualization"
        },
        {
          "id": "833e0110-b9ec-11e9-b6a2-c9b4015c4baf",
          "name": "panel_1",
          "type": "visualization"
        },
        {
          "id": "5e7f0ed0-bcd2-11e9-b6a2-c9b4015c4baf",
          "name": "panel_2",
          "type": "visualization"
        },
        {
          "id": "b2cecf10-bcd3-11e9-b6a2-c9b4015c4baf",
          "name": "panel_3",
          "type": "visualization"
        },
        {
          "id": "0620c3d0-bcd4-11e9-b6a2-c9b4015c4baf",
          "name": "panel_4",
          "type": "visualization"
        },
        {
          "id": "8f20c950-bcd4-11e9-b6a2-c9b4015c4baf",
          "name": "panel_5",
          "type": "visualization"
        },
        {
          "id": "ee0319a0-bcd4-11e9-b6a2-c9b4015c4baf",
          "name": "panel_6",
          "type": "visualization"
        },
        {
          "id": "dce77e60-bcd7-11e9-b6a2-c9b4015c4baf",
          "name": "panel_7",
          "type": "visualization"
        },
        {
          "id": "da5ffe40-bcd9-11e9-b6a2-c9b4015c4baf",
          "name": "panel_8",
          "type": "visualization"
        },
        {
          "id": "da2110c0-bcea-11e9-b6a2-c9b4015c4baf",
          "name": "panel_9",
          "type": "visualization"
        },
        {
          "id": "abf96c10-bcea-11e9-b6a2-c9b4015c4baf",
          "name": "panel_10",
          "type": "visualization"
        },
        {
          "id": "4ac8f5f0-bcfe-11e9-b6a2-c9b4015c4baf",
          "name": "panel_11",
          "type": "visualization"
        },
        {
          "id": "8f723a10-bd97-11e9-b9c5-fddc96658612",
          "name": "panel_12",
          "type": "visualization"
        },
        {
          "id": "7e178c80-fee1-11e9-8405-516218e3d268",
          "name": "panel_13",
          "type": "search"
        },
        {
          "id": "324686c0-fefb-11e9-8405-516218e3d268",
          "name": "panel_14",
          "type": "search"
        },
        {
          "id": "97c70300-ff1c-11e9-8405-516218e3d268",
          "name": "panel_15",
          "type": "visualization"
        },
        {
          "id": "bf45dc50-ff1a-11e9-8405-516218e3d268",
          "name": "panel_16",
          "type": "visualization"
        },
        {
          "id": "7322f9f0-ff1c-11e9-8405-516218e3d268",
          "name": "panel_17",
          "type": "visualization"
        },
        {
          "id": "d3a5fec0-ff18-11e9-8405-516218e3d268",
          "name": "panel_18",
          "type": "visualization"
        },
        {
          "id": "1b6725f0-ff1d-11e9-8405-516218e3d268",
          "name": "panel_19",
          "type": "visualization"
        },
        {
          "id": "60301890-ff1d-11e9-8405-516218e3d268",
          "name": "panel_20",
          "type": "visualization"
        },
        {
          "id": "9dd22440-ff1d-11e9-8405-516218e3d268",
          "name": "panel_21",
          "type": "visualization"
        },
        {
          "id": "c9d959f0-ff1d-11e9-8405-516218e3d268",
          "name": "panel_22",
          "type": "visualization"
        }
      ],
      "type": "dashboard",
      "updated_at": "2019-11-05T15:40:21.391Z",
      "version": "WzU2MiwxXQ=="
    },
    {
      "attributes": {
        "description": "",
        "kibanaSavedObjectMeta": {
          "searchSourceJSON": "{\"query\":{\"language\":\"kuery\",\"query\":\"\"},\"filter\":[]}"
        },
        "title": "User  Management Events - Description",
        "uiStateJSON": "{}",
        "version": 1,
        "visState": "{\"title\":\"User  Management Events - Description\",\"type\":\"markdown\",\"params\":{\"markdown\":\"# **User Management Events**\\n\\n#### This dashboard shows information about User Management Events collected by winlogbeat\\n#\\n#\\n#\\nEvent | Description\\n-- | --\\n4720 | A user account was created\\n4722 | A user account was enabled\\n4723 | An attempt was made to change an account's password\\n4724 | An attempt was made to reset an account's password\\n4725 | An user account was disabled\\n4726 | An user account was deleted\\n4738 | An user account was changed\\n4740 | An user account was locked out\\n4767 | An account was unlocked\\n4781 | The name of an account was changed\",\"openLinksInNewTab\":false,\"fontSize\":10},\"aggs\":[]}"
      },
      "id": "2dc6b820-b9e8-11e9-b6a2-c9b4015c4baf",
      "migrationVersion": {
        "visualization": "7.3.1"
      },
      "references": [],
      "type": "visualization",
      "updated_at": "2019-11-04T10:20:41.549Z",
      "version": "WzQxNywxXQ=="
    },
    {
      "attributes": {
        "description": "",
        "kibanaSavedObjectMeta": {
          "searchSourceJSON": "{\"query\":{\"query\":\"\",\"language\":\"kuery\"},\"filter\":[{\"meta\":{\"type\":\"phrases\",\"key\":\"event.code\",\"value\":\"4720, 4722, 4723, 4724, 4725, 4726, 4738, 4740, 4765, 4766, 4767, 4780, 4781, 4794, 5376, 5377\",\"params\":[\"4720\",\"4722\",\"4723\",\"4724\",\"4725\",\"4726\",\"4738\",\"4740\",\"4765\",\"4766\",\"4767\",\"4780\",\"4781\",\"4794\",\"5376\",\"5377\"],\"alias\":null,\"negate\":false,\"disabled\":false,\"indexRefName\":\"kibanaSavedObjectMeta.searchSourceJSON.filter[0].meta.index\"},\"query\":{\"bool\":{\"should\":[{\"match_phrase\":{\"event.code\":\"4720\"}},{\"match_phrase\":{\"event.code\":\"4722\"}},{\"match_phrase\":{\"event.code\":\"4723\"}},{\"match_phrase\":{\"event.code\":\"4724\"}},{\"match_phrase\":{\"event.code\":\"4725\"}},{\"match_phrase\":{\"event.code\":\"4726\"}},{\"match_phrase\":{\"event.code\":\"4738\"}},{\"match_phrase\":{\"event.code\":\"4740\"}},{\"match_phrase\":{\"event.code\":\"4765\"}},{\"match_phrase\":{\"event.code\":\"4766\"}},{\"match_phrase\":{\"event.code\":\"4767\"}},{\"match_phrase\":{\"event.code\":\"4780\"}},{\"match_phrase\":{\"event.code\":\"4781\"}},{\"match_phrase\":{\"event.code\":\"4794\"}},{\"match_phrase\":{\"event.code\":\"5376\"}},{\"match_phrase\":{\"event.code\":\"5377\"}}],\"minimum_should_match\":1}},\"$state\":{\"store\":\"appState\"}}],\"indexRefName\":\"kibanaSavedObjectMeta.searchSourceJSON.index\"}"
        },
        "title": "User Management Events - Event Actions - Donut",
        "uiStateJSON": "{}",
        "version": 1,
        "visState": "{\"title\":\"User Management Events - Event Actions - Donut\",\"type\":\"pie\",\"params\":{\"addLegend\":true,\"addTooltip\":true,\"dimensions\":{\"metric\":{\"accessor\":1,\"format\":{\"id\":\"number\"},\"params\":{},\"aggType\":\"count\"},\"buckets\":[{\"accessor\":0,\"format\":{\"id\":\"terms\",\"params\":{\"id\":\"string\",\"otherBucketLabel\":\"Other\",\"missingBucketLabel\":\"Missing\"}},\"params\":{},\"aggType\":\"terms\"}]},\"isDonut\":true,\"labels\":{\"last_level\":true,\"show\":true,\"truncate\":100,\"values\":true},\"legendPosition\":\"right\",\"type\":\"pie\"},\"aggs\":[{\"id\":\"1\",\"enabled\":true,\"type\":\"count\",\"schema\":\"metric\",\"params\":{}},{\"id\":\"2\",\"enabled\":true,\"type\":\"terms\",\"schema\":\"segment\",\"params\":{\"field\":\"event.action\",\"orderBy\":\"1\",\"order\":\"desc\",\"size\":5,\"otherBucket\":false,\"otherBucketLabel\":\"Other\",\"missingBucket\":false,\"missingBucketLabel\":\"Missing\"}}]}"
      },
      "id": "833e0110-b9ec-11e9-b6a2-c9b4015c4baf",
      "migrationVersion": {
        "visualization": "7.3.1"
      },
      "references": [
        {
          "id": "winlogbeat-*",
          "name": "kibanaSavedObjectMeta.searchSourceJSON.index",
          "type": "index-pattern"
        },
        {
          "id": "winlogbeat-*",
          "name": "kibanaSavedObjectMeta.searchSourceJSON.filter[0].meta.index",
          "type": "index-pattern"
        }
      ],
      "type": "visualization",
      "updated_at": "2019-11-04T11:13:23.297Z",
      "version": "WzQ2NiwxXQ=="
    },
    {
      "attributes": {
        "description": "",
        "kibanaSavedObjectMeta": {
          "searchSourceJSON": "{\"query\":{\"query\":\"\",\"language\":\"kuery\"},\"filter\":[{\"meta\":{\"alias\":null,\"negate\":false,\"type\":\"phrase\",\"key\":\"event.code\",\"value\":\"4720\",\"params\":{\"query\":\"4720\"},\"disabled\":false,\"indexRefName\":\"kibanaSavedObjectMeta.searchSourceJSON.filter[0].meta.index\"},\"query\":{\"match\":{\"event.code\":{\"query\":\"4720\",\"type\":\"phrase\"}}},\"$state\":{\"store\":\"appState\"}}],\"indexRefName\":\"kibanaSavedObjectMeta.searchSourceJSON.index\"}"
        },
        "title": "Users Created - Table",
        "uiStateJSON": "{\"vis\":{\"params\":{\"sort\":{\"columnIndex\":null,\"direction\":null}}}}",
        "version": 1,
        "visState": "{\"title\":\"Users Created - Table\",\"type\":\"table\",\"params\":{\"perPage\":10,\"showPartialRows\":false,\"showMetricsAtAllLevels\":false,\"sort\":{\"columnIndex\":null,\"direction\":null},\"showTotal\":false,\"totalFunc\":\"sum\",\"dimensions\":{\"metrics\":[{\"accessor\":3,\"format\":{\"id\":\"number\"},\"params\":{},\"aggType\":\"count\"}],\"buckets\":[{\"accessor\":0,\"format\":{\"id\":\"terms\",\"params\":{\"id\":\"string\",\"otherBucketLabel\":\"Other\",\"missingBucketLabel\":\"Missing\"}},\"params\":{},\"aggType\":\"terms\"},{\"accessor\":1,\"format\":{\"id\":\"terms\",\"params\":{\"id\":\"string\",\"otherBucketLabel\":\"Other\",\"missingBucketLabel\":\"Missing\"}},\"params\":{},\"aggType\":\"terms\"},{\"accessor\":2,\"format\":{\"id\":\"terms\",\"params\":{\"id\":\"string\",\"otherBucketLabel\":\"Other\",\"missingBucketLabel\":\"Missing\"}},\"params\":{},\"aggType\":\"terms\"}]}},\"aggs\":[{\"id\":\"1\",\"enabled\":true,\"type\":\"count\",\"schema\":\"metric\",\"params\":{}},{\"id\":\"2\",\"enabled\":true,\"type\":\"terms\",\"schema\":\"bucket\",\"params\":{\"field\":\"user.name\",\"orderBy\":\"1\",\"order\":\"desc\",\"size\":100,\"otherBucket\":false,\"otherBucketLabel\":\"Other\",\"missingBucket\":false,\"missingBucketLabel\":\"Missing\",\"customLabel\":\"Created User\"}},{\"id\":\"3\",\"enabled\":true,\"type\":\"terms\",\"schema\":\"bucket\",\"params\":{\"field\":\"winlog.event_data.SubjectUserName\",\"orderBy\":\"1\",\"order\":\"desc\",\"size\":5,\"otherBucket\":false,\"otherBucketLabel\":\"Other\",\"missingBucket\":true,\"missingBucketLabel\":\"Missing\",\"customLabel\":\"Performed by\"}},{\"id\":\"4\",\"enabled\":true,\"type\":\"terms\",\"schema\":\"bucket\",\"params\":{\"field\":\"winlog.logon.id\",\"orderBy\":\"1\",\"order\":\"desc\",\"size\":5,\"otherBucket\":false,\"otherBucketLabel\":\"Other\",\"missingBucket\":false,\"missingBucketLabel\":\"Missing\",\"customLabel\":\"Performer LogonID\"}}]}"
      },
      "id": "5e7f0ed0-bcd2-11e9-b6a2-c9b4015c4baf",
      "migrationVersion": {
        "visualization": "7.3.1"
      },
      "references": [
        {
          "id": "winlogbeat-*",
          "name": "kibanaSavedObjectMeta.searchSourceJSON.index",
          "type": "index-pattern"
        },
        {
          "id": "winlogbeat-*",
          "name": "kibanaSavedObjectMeta.searchSourceJSON.filter[0].meta.index",
          "type": "index-pattern"
        }
      ],
      "type": "visualization",
      "updated_at": "2019-11-04T14:35:21.465Z",
      "version": "WzQ4NSwxXQ=="
    },
    {
      "attributes": {
        "description": "",
        "kibanaSavedObjectMeta": {
          "searchSourceJSON": "{\"query\":{\"query\":\"\",\"language\":\"kuery\"},\"filter\":[{\"meta\":{\"type\":\"phrases\",\"key\":\"event.code\",\"value\":\"4720, 4722, 4723, 4724, 4725, 4726, 4738, 4740, 4765, 4766, 4767, 4780, 4781, 4794, 5376, 5377\",\"params\":[\"4720\",\"4722\",\"4723\",\"4724\",\"4725\",\"4726\",\"4738\",\"4740\",\"4765\",\"4766\",\"4767\",\"4780\",\"4781\",\"4794\",\"5376\",\"5377\"],\"alias\":null,\"negate\":false,\"disabled\":false,\"indexRefName\":\"kibanaSavedObjectMeta.searchSourceJSON.filter[0].meta.index\"},\"query\":{\"bool\":{\"should\":[{\"match_phrase\":{\"event.code\":\"4720\"}},{\"match_phrase\":{\"event.code\":\"4722\"}},{\"match_phrase\":{\"event.code\":\"4723\"}},{\"match_phrase\":{\"event.code\":\"4724\"}},{\"match_phrase\":{\"event.code\":\"4725\"}},{\"match_phrase\":{\"event.code\":\"4726\"}},{\"match_phrase\":{\"event.code\":\"4738\"}},{\"match_phrase\":{\"event.code\":\"4740\"}},{\"match_phrase\":{\"event.code\":\"4765\"}},{\"match_phrase\":{\"event.code\":\"4766\"}},{\"match_phrase\":{\"event.code\":\"4767\"}},{\"match_phrase\":{\"event.code\":\"4780\"}},{\"match_phrase\":{\"event.code\":\"4781\"}},{\"match_phrase\":{\"event.code\":\"4794\"}},{\"match_phrase\":{\"event.code\":\"5376\"}},{\"match_phrase\":{\"event.code\":\"5377\"}}],\"minimum_should_match\":1}},\"$state\":{\"store\":\"appState\"}}],\"indexRefName\":\"kibanaSavedObjectMeta.searchSourceJSON.index\"}"
        },
        "title": "User Management Events - Event Actions - Table",
        "uiStateJSON": "{\"vis\":{\"params\":{\"sort\":{\"columnIndex\":null,\"direction\":null}}}}",
        "version": 1,
        "visState": "{\"title\":\"User Management Events - Event Actions - Table\",\"type\":\"table\",\"params\":{\"dimensions\":{\"buckets\":[{\"accessor\":0,\"aggType\":\"terms\",\"format\":{\"id\":\"terms\",\"params\":{\"id\":\"string\",\"missingBucketLabel\":\"Missing\",\"otherBucketLabel\":\"Other\"}},\"params\":{}},{\"accessor\":1,\"aggType\":\"terms\",\"format\":{\"id\":\"terms\",\"params\":{\"id\":\"string\",\"missingBucketLabel\":\"Missing\",\"otherBucketLabel\":\"Other\"}},\"params\":{}}],\"metrics\":[{\"accessor\":2,\"aggType\":\"count\",\"format\":{\"id\":\"number\"},\"params\":{}}]},\"perPage\":10,\"showMetricsAtAllLevels\":false,\"showPartialRows\":false,\"showTotal\":false,\"sort\":{\"columnIndex\":null,\"direction\":null},\"totalFunc\":\"sum\"},\"aggs\":[{\"id\":\"1\",\"enabled\":true,\"type\":\"count\",\"schema\":\"metric\",\"params\":{}},{\"id\":\"2\",\"enabled\":true,\"type\":\"terms\",\"schema\":\"bucket\",\"params\":{\"field\":\"event.action\",\"orderBy\":\"1\",\"order\":\"desc\",\"size\":10,\"otherBucket\":false,\"otherBucketLabel\":\"Other\",\"missingBucket\":false,\"missingBucketLabel\":\"Missing\",\"customLabel\":\"Event Short Description\"}},{\"id\":\"3\",\"enabled\":true,\"type\":\"terms\",\"schema\":\"bucket\",\"params\":{\"field\":\"event.code\",\"orderBy\":\"1\",\"order\":\"desc\",\"size\":5,\"otherBucket\":false,\"otherBucketLabel\":\"Other\",\"missingBucket\":false,\"missingBucketLabel\":\"Missing\",\"customLabel\":\"Event Code\"}}]}"
      },
      "id": "b2cecf10-bcd3-11e9-b6a2-c9b4015c4baf",
      "migrationVersion": {
        "visualization": "7.3.1"
      },
      "references": [
        {
          "id": "winlogbeat-*",
          "name": "kibanaSavedObjectMeta.searchSourceJSON.index",
          "type": "index-pattern"
        },
        {
          "id": "winlogbeat-*",
          "name": "kibanaSavedObjectMeta.searchSourceJSON.filter[0].meta.index",
          "type": "index-pattern"
        }
      ],
      "type": "visualization",
      "updated_at": "2019-11-04T10:23:43.282Z",
      "version": "WzQyMiwxXQ=="
    },
    {
      "attributes": {
        "description": "",
        "kibanaSavedObjectMeta": {
          "searchSourceJSON": "{\"query\":{\"query\":\"\",\"language\":\"kuery\"},\"filter\":[{\"meta\":{\"alias\":null,\"negate\":false,\"type\":\"phrase\",\"key\":\"event.code\",\"value\":\"4722\",\"params\":{\"query\":\"4722\"},\"disabled\":false,\"indexRefName\":\"kibanaSavedObjectMeta.searchSourceJSON.filter[0].meta.index\"},\"query\":{\"match\":{\"event.code\":{\"query\":\"4722\",\"type\":\"phrase\"}}},\"$state\":{\"store\":\"appState\"}}],\"indexRefName\":\"kibanaSavedObjectMeta.searchSourceJSON.index\"}"
        },
        "title": "Users Enabled - Table",
        "uiStateJSON": "{\"vis\":{\"params\":{\"sort\":{\"columnIndex\":null,\"direction\":null}}}}",
        "version": 1,
        "visState": "{\"title\":\"Users Enabled - Table\",\"type\":\"table\",\"params\":{\"perPage\":10,\"showPartialRows\":false,\"showMetricsAtAllLevels\":false,\"sort\":{\"columnIndex\":null,\"direction\":null},\"showTotal\":false,\"totalFunc\":\"sum\",\"dimensions\":{\"metrics\":[{\"accessor\":3,\"format\":{\"id\":\"number\"},\"params\":{},\"aggType\":\"count\"}],\"buckets\":[{\"accessor\":0,\"format\":{\"id\":\"terms\",\"params\":{\"id\":\"string\",\"otherBucketLabel\":\"Other\",\"missingBucketLabel\":\"Missing\"}},\"params\":{},\"aggType\":\"terms\"},{\"accessor\":1,\"format\":{\"id\":\"terms\",\"params\":{\"id\":\"string\",\"otherBucketLabel\":\"Other\",\"missingBucketLabel\":\"Missing\"}},\"params\":{},\"aggType\":\"terms\"},{\"accessor\":2,\"format\":{\"id\":\"terms\",\"params\":{\"id\":\"string\",\"otherBucketLabel\":\"Other\",\"missingBucketLabel\":\"Missing\"}},\"params\":{},\"aggType\":\"terms\"}]}},\"aggs\":[{\"id\":\"1\",\"enabled\":true,\"type\":\"count\",\"schema\":\"metric\",\"params\":{}},{\"id\":\"2\",\"enabled\":true,\"type\":\"terms\",\"schema\":\"bucket\",\"params\":{\"field\":\"user.name\",\"orderBy\":\"1\",\"order\":\"desc\",\"size\":100,\"otherBucket\":false,\"otherBucketLabel\":\"Other\",\"missingBucket\":false,\"missingBucketLabel\":\"Missing\",\"customLabel\":\"Enabled User\"}},{\"id\":\"3\",\"enabled\":true,\"type\":\"terms\",\"schema\":\"bucket\",\"params\":{\"field\":\"winlog.event_data.SubjectUserName\",\"orderBy\":\"1\",\"order\":\"desc\",\"size\":5,\"otherBucket\":false,\"otherBucketLabel\":\"Other\",\"missingBucket\":true,\"missingBucketLabel\":\"Missing\",\"customLabel\":\"Performed by\"}},{\"id\":\"4\",\"enabled\":true,\"type\":\"terms\",\"schema\":\"bucket\",\"params\":{\"field\":\"winlog.logon.id\",\"orderBy\":\"1\",\"order\":\"desc\",\"size\":5,\"otherBucket\":false,\"otherBucketLabel\":\"Other\",\"missingBucket\":false,\"missingBucketLabel\":\"Missing\",\"customLabel\":\"Performer LogonId\"}}]}"
      },
      "id": "0620c3d0-bcd4-11e9-b6a2-c9b4015c4baf",
      "migrationVersion": {
        "visualization": "7.3.1"
      },
      "references": [
        {
          "id": "winlogbeat-*",
          "name": "kibanaSavedObjectMeta.searchSourceJSON.index",
          "type": "index-pattern"
        },
        {
          "id": "winlogbeat-*",
          "name": "kibanaSavedObjectMeta.searchSourceJSON.filter[0].meta.index",
          "type": "index-pattern"
        }
      ],
      "type": "visualization",
      "updated_at": "2019-11-04T14:37:53.874Z",
      "version": "WzQ4NywxXQ=="
    },
    {
      "attributes": {
        "description": "",
        "kibanaSavedObjectMeta": {
          "searchSourceJSON": "{\"query\":{\"query\":\"\",\"language\":\"kuery\"},\"filter\":[{\"meta\":{\"alias\":null,\"negate\":false,\"type\":\"phrase\",\"key\":\"event.code\",\"value\":\"4725\",\"params\":{\"query\":\"4725\"},\"disabled\":false,\"indexRefName\":\"kibanaSavedObjectMeta.searchSourceJSON.filter[0].meta.index\"},\"query\":{\"match\":{\"event.code\":{\"query\":\"4725\",\"type\":\"phrase\"}}},\"$state\":{\"store\":\"appState\"}}],\"indexRefName\":\"kibanaSavedObjectMeta.searchSourceJSON.index\"}"
        },
        "title": "Users Disabled - Table",
        "uiStateJSON": "{\"vis\":{\"params\":{\"sort\":{\"columnIndex\":null,\"direction\":null}}}}",
        "version": 1,
        "visState": "{\"title\":\"Users Disabled - Table\",\"type\":\"table\",\"params\":{\"perPage\":10,\"showPartialRows\":false,\"showMetricsAtAllLevels\":false,\"sort\":{\"columnIndex\":null,\"direction\":null},\"showTotal\":false,\"totalFunc\":\"sum\",\"dimensions\":{\"metrics\":[{\"accessor\":3,\"format\":{\"id\":\"number\"},\"params\":{},\"aggType\":\"count\"}],\"buckets\":[{\"accessor\":0,\"format\":{\"id\":\"terms\",\"params\":{\"id\":\"string\",\"otherBucketLabel\":\"Other\",\"missingBucketLabel\":\"Missing\"}},\"params\":{},\"aggType\":\"terms\"},{\"accessor\":1,\"format\":{\"id\":\"terms\",\"params\":{\"id\":\"string\",\"otherBucketLabel\":\"Other\",\"missingBucketLabel\":\"Missing\"}},\"params\":{},\"aggType\":\"terms\"},{\"accessor\":2,\"format\":{\"id\":\"terms\",\"params\":{\"id\":\"string\",\"otherBucketLabel\":\"Other\",\"missingBucketLabel\":\"Missing\"}},\"params\":{},\"aggType\":\"terms\"}]}},\"aggs\":[{\"id\":\"1\",\"enabled\":true,\"type\":\"count\",\"schema\":\"metric\",\"params\":{}},{\"id\":\"2\",\"enabled\":true,\"type\":\"terms\",\"schema\":\"bucket\",\"params\":{\"field\":\"user.name\",\"orderBy\":\"1\",\"order\":\"desc\",\"size\":100,\"otherBucket\":false,\"otherBucketLabel\":\"Other\",\"missingBucket\":false,\"missingBucketLabel\":\"Missing\",\"customLabel\":\"Disabled User\"}},{\"id\":\"3\",\"enabled\":true,\"type\":\"terms\",\"schema\":\"bucket\",\"params\":{\"field\":\"winlog.event_data.SubjectUserName\",\"orderBy\":\"1\",\"order\":\"desc\",\"size\":5,\"otherBucket\":false,\"otherBucketLabel\":\"Other\",\"missingBucket\":true,\"missingBucketLabel\":\"Missing\",\"customLabel\":\"Performed by\"}},{\"id\":\"4\",\"enabled\":true,\"type\":\"terms\",\"schema\":\"bucket\",\"params\":{\"field\":\"winlog.logon.id\",\"orderBy\":\"1\",\"order\":\"desc\",\"size\":5,\"otherBucket\":false,\"otherBucketLabel\":\"Other\",\"missingBucket\":false,\"missingBucketLabel\":\"Missing\",\"customLabel\":\"Performer LogonId\"}}]}"
      },
      "id": "8f20c950-bcd4-11e9-b6a2-c9b4015c4baf",
      "migrationVersion": {
        "visualization": "7.3.1"
      },
      "references": [
        {
          "id": "winlogbeat-*",
          "name": "kibanaSavedObjectMeta.searchSourceJSON.index",
          "type": "index-pattern"
        },
        {
          "id": "winlogbeat-*",
          "name": "kibanaSavedObjectMeta.searchSourceJSON.filter[0].meta.index",
          "type": "index-pattern"
        }
      ],
      "type": "visualization",
      "updated_at": "2019-11-04T15:15:00.943Z",
      "version": "WzUwNCwxXQ=="
    },
    {
      "attributes": {
        "description": "",
        "kibanaSavedObjectMeta": {
          "searchSourceJSON": "{\"query\":{\"query\":\"\",\"language\":\"kuery\"},\"filter\":[{\"meta\":{\"alias\":null,\"negate\":false,\"type\":\"phrase\",\"key\":\"event.code\",\"value\":\"4726\",\"params\":{\"query\":\"4726\"},\"disabled\":false,\"indexRefName\":\"kibanaSavedObjectMeta.searchSourceJSON.filter[0].meta.index\"},\"query\":{\"match\":{\"event.code\":{\"query\":\"4726\",\"type\":\"phrase\"}}},\"$state\":{\"store\":\"appState\"}}],\"indexRefName\":\"kibanaSavedObjectMeta.searchSourceJSON.index\"}"
        },
        "title": "Users Deleted - Table",
        "uiStateJSON": "{\"vis\":{\"params\":{\"sort\":{\"columnIndex\":null,\"direction\":null}}}}",
        "version": 1,
        "visState": "{\"title\":\"Users Deleted - Table\",\"type\":\"table\",\"params\":{\"perPage\":10,\"showPartialRows\":false,\"showMetricsAtAllLevels\":false,\"sort\":{\"columnIndex\":null,\"direction\":null},\"showTotal\":false,\"totalFunc\":\"sum\",\"dimensions\":{\"metrics\":[{\"accessor\":3,\"format\":{\"id\":\"number\"},\"params\":{},\"aggType\":\"count\"}],\"buckets\":[{\"accessor\":0,\"format\":{\"id\":\"terms\",\"params\":{\"id\":\"string\",\"otherBucketLabel\":\"Other\",\"missingBucketLabel\":\"Missing\"}},\"params\":{},\"aggType\":\"terms\"},{\"accessor\":1,\"format\":{\"id\":\"terms\",\"params\":{\"id\":\"string\",\"otherBucketLabel\":\"Other\",\"missingBucketLabel\":\"Missing\"}},\"params\":{},\"aggType\":\"terms\"},{\"accessor\":2,\"format\":{\"id\":\"terms\",\"params\":{\"id\":\"string\",\"otherBucketLabel\":\"Other\",\"missingBucketLabel\":\"Missing\"}},\"params\":{},\"aggType\":\"terms\"}]}},\"aggs\":[{\"id\":\"1\",\"enabled\":true,\"type\":\"count\",\"schema\":\"metric\",\"params\":{}},{\"id\":\"2\",\"enabled\":true,\"type\":\"terms\",\"schema\":\"bucket\",\"params\":{\"field\":\"user.name\",\"orderBy\":\"1\",\"order\":\"desc\",\"size\":100,\"otherBucket\":false,\"otherBucketLabel\":\"Other\",\"missingBucket\":false,\"missingBucketLabel\":\"Missing\",\"customLabel\":\"Deleted User\"}},{\"id\":\"3\",\"enabled\":true,\"type\":\"terms\",\"schema\":\"bucket\",\"params\":{\"field\":\"winlog.event_data.SubjectUserName\",\"orderBy\":\"1\",\"order\":\"desc\",\"size\":5,\"otherBucket\":false,\"otherBucketLabel\":\"Other\",\"missingBucket\":true,\"missingBucketLabel\":\"Missing\",\"customLabel\":\"Performed by\"}},{\"id\":\"4\",\"enabled\":true,\"type\":\"terms\",\"schema\":\"bucket\",\"params\":{\"field\":\"winlog.logon.id\",\"orderBy\":\"1\",\"order\":\"desc\",\"size\":5,\"otherBucket\":false,\"otherBucketLabel\":\"Other\",\"missingBucket\":false,\"missingBucketLabel\":\"Missing\",\"customLabel\":\"Performed LogonId\"}}]}"
      },
      "id": "ee0319a0-bcd4-11e9-b6a2-c9b4015c4baf",
      "migrationVersion": {
        "visualization": "7.3.1"
      },
      "references": [
        {
          "id": "winlogbeat-*",
          "name": "kibanaSavedObjectMeta.searchSourceJSON.index",
          "type": "index-pattern"
        },
        {
          "id": "winlogbeat-*",
          "name": "kibanaSavedObjectMeta.searchSourceJSON.filter[0].meta.index",
          "type": "index-pattern"
        }
      ],
      "type": "visualization",
      "updated_at": "2019-11-04T14:44:25.678Z",
      "version": "WzQ5MywxXQ=="
    },
    {
      "attributes": {
        "description": "",
        "kibanaSavedObjectMeta": {
          "searchSourceJSON": "{\"query\":{\"query\":\"\",\"language\":\"kuery\"},\"filter\":[{\"meta\":{\"type\":\"phrases\",\"key\":\"event.code\",\"value\":\"4720, 4722, 4723, 4724, 4725, 4726, 4738, 4740, 4765, 4766, 4767, 4780, 4781, 4794, 5376, 5377\",\"params\":[\"4720\",\"4722\",\"4723\",\"4724\",\"4725\",\"4726\",\"4738\",\"4740\",\"4765\",\"4766\",\"4767\",\"4780\",\"4781\",\"4794\",\"5376\",\"5377\"],\"alias\":null,\"negate\":false,\"disabled\":false,\"indexRefName\":\"kibanaSavedObjectMeta.searchSourceJSON.filter[0].meta.index\"},\"query\":{\"bool\":{\"should\":[{\"match_phrase\":{\"event.code\":\"4720\"}},{\"match_phrase\":{\"event.code\":\"4722\"}},{\"match_phrase\":{\"event.code\":\"4723\"}},{\"match_phrase\":{\"event.code\":\"4724\"}},{\"match_phrase\":{\"event.code\":\"4725\"}},{\"match_phrase\":{\"event.code\":\"4726\"}},{\"match_phrase\":{\"event.code\":\"4738\"}},{\"match_phrase\":{\"event.code\":\"4740\"}},{\"match_phrase\":{\"event.code\":\"4765\"}},{\"match_phrase\":{\"event.code\":\"4766\"}},{\"match_phrase\":{\"event.code\":\"4767\"}},{\"match_phrase\":{\"event.code\":\"4780\"}},{\"match_phrase\":{\"event.code\":\"4781\"}},{\"match_phrase\":{\"event.code\":\"4794\"}},{\"match_phrase\":{\"event.code\":\"5376\"}},{\"match_phrase\":{\"event.code\":\"5377\"}}],\"minimum_should_match\":1}},\"$state\":{\"store\":\"appState\"}}],\"indexRefName\":\"kibanaSavedObjectMeta.searchSourceJSON.index\"}"
        },
        "title": "User Management Events - Affected Users vs Actions - Heatmap",
        "uiStateJSON": "{\"vis\":{\"defaultColors\":{\"0 - 14\":\"rgb(247,251,255)\",\"14 - 28\":\"rgb(198,219,239)\",\"28 - 42\":\"rgb(107,174,214)\",\"42 - 55\":\"rgb(33,113,181)\"}}}",
        "version": 1,
        "visState": "{\"title\":\"User Management Events - Affected Users vs Actions - Heatmap\",\"type\":\"heatmap\",\"params\":{\"type\":\"heatmap\",\"addTooltip\":true,\"addLegend\":true,\"enableHover\":false,\"legendPosition\":\"right\",\"times\":[],\"colorsNumber\":4,\"colorSchema\":\"Blues\",\"setColorRange\":false,\"colorsRange\":[],\"invertColors\":false,\"percentageMode\":false,\"valueAxes\":[{\"show\":false,\"id\":\"ValueAxis-1\",\"type\":\"value\",\"scale\":{\"type\":\"linear\",\"defaultYExtents\":false},\"labels\":{\"show\":true,\"rotate\":0,\"overwriteColor\":false,\"color\":\"black\"}}],\"dimensions\":{\"x\":{\"accessor\":0,\"format\":{\"id\":\"terms\",\"params\":{\"id\":\"string\",\"otherBucketLabel\":\"Other\",\"missingBucketLabel\":\"Missing\"}},\"params\":{},\"aggType\":\"terms\"},\"y\":[{\"accessor\":2,\"format\":{\"id\":\"number\"},\"params\":{},\"aggType\":\"count\"}],\"series\":[{\"accessor\":1,\"format\":{\"id\":\"terms\",\"params\":{\"id\":\"string\",\"otherBucketLabel\":\"Other\",\"missingBucketLabel\":\"Missing\"}},\"params\":{},\"aggType\":\"terms\"}]}},\"aggs\":[{\"id\":\"1\",\"enabled\":true,\"type\":\"count\",\"schema\":\"metric\",\"params\":{}},{\"id\":\"2\",\"enabled\":true,\"type\":\"terms\",\"schema\":\"segment\",\"params\":{\"field\":\"user.name\",\"orderBy\":\"1\",\"order\":\"desc\",\"size\":10,\"otherBucket\":false,\"otherBucketLabel\":\"Other\",\"missingBucket\":false,\"missingBucketLabel\":\"Missing\",\"customLabel\":\"Target User\"}},{\"id\":\"3\",\"enabled\":true,\"type\":\"terms\",\"schema\":\"group\",\"params\":{\"field\":\"event.action\",\"orderBy\":\"1\",\"order\":\"desc\",\"size\":5,\"otherBucket\":false,\"otherBucketLabel\":\"Other\",\"missingBucket\":false,\"missingBucketLabel\":\"Missing\",\"customLabel\":\"Operation\"}}]}"
      },
      "id": "dce77e60-bcd7-11e9-b6a2-c9b4015c4baf",
      "migrationVersion": {
        "visualization": "7.3.1"
      },
      "references": [
        {
          "id": "winlogbeat-*",
          "name": "kibanaSavedObjectMeta.searchSourceJSON.index",
          "type": "index-pattern"
        },
        {
          "id": "winlogbeat-*",
          "name": "kibanaSavedObjectMeta.searchSourceJSON.filter[0].meta.index",
          "type": "index-pattern"
        }
      ],
      "type": "visualization",
      "updated_at": "2019-11-04T10:24:35.247Z",
      "version": "WzQyNCwxXQ=="
    },
    {
      "attributes": {
        "description": "",
        "kibanaSavedObjectMeta": {
          "searchSourceJSON": "{\"query\":{\"query\":\"\",\"language\":\"kuery\"},\"filter\":[{\"meta\":{\"type\":\"phrases\",\"key\":\"event.code\",\"value\":\"4723, 4724\",\"params\":[\"4723\",\"4724\"],\"alias\":null,\"negate\":false,\"disabled\":false,\"indexRefName\":\"kibanaSavedObjectMeta.searchSourceJSON.filter[0].meta.index\"},\"query\":{\"bool\":{\"should\":[{\"match_phrase\":{\"event.code\":\"4723\"}},{\"match_phrase\":{\"event.code\":\"4724\"}}],\"minimum_should_match\":1}},\"$state\":{\"store\":\"appState\"}}],\"indexRefName\":\"kibanaSavedObjectMeta.searchSourceJSON.index\"}"
        },
        "title": "Users Password Changes - Table",
        "uiStateJSON": "{\"vis\":{\"params\":{\"sort\":{\"columnIndex\":null,\"direction\":null}}}}",
        "version": 1,
        "visState": "{\"title\":\"Users Password Changes - Table\",\"type\":\"table\",\"params\":{\"perPage\":10,\"showPartialRows\":false,\"showMetricsAtAllLevels\":false,\"sort\":{\"columnIndex\":null,\"direction\":null},\"showTotal\":false,\"totalFunc\":\"sum\",\"dimensions\":{\"metrics\":[{\"accessor\":3,\"format\":{\"id\":\"number\"},\"params\":{},\"aggType\":\"count\"}],\"buckets\":[{\"accessor\":0,\"format\":{\"id\":\"terms\",\"params\":{\"id\":\"string\",\"otherBucketLabel\":\"Other\",\"missingBucketLabel\":\"Missing\"}},\"params\":{},\"aggType\":\"terms\"},{\"accessor\":1,\"format\":{\"id\":\"terms\",\"params\":{\"id\":\"string\",\"otherBucketLabel\":\"Other\",\"missingBucketLabel\":\"Missing\"}},\"params\":{},\"aggType\":\"terms\"},{\"accessor\":2,\"format\":{\"id\":\"terms\",\"params\":{\"id\":\"string\",\"otherBucketLabel\":\"Other\",\"missingBucketLabel\":\"Missing\"}},\"params\":{},\"aggType\":\"terms\"}]}},\"aggs\":[{\"id\":\"1\",\"enabled\":true,\"type\":\"count\",\"schema\":\"metric\",\"params\":{}},{\"id\":\"2\",\"enabled\":true,\"type\":\"terms\",\"schema\":\"bucket\",\"params\":{\"field\":\"user.name\",\"orderBy\":\"1\",\"order\":\"desc\",\"size\":100,\"otherBucket\":false,\"otherBucketLabel\":\"Other\",\"missingBucket\":false,\"missingBucketLabel\":\"Missing\",\"customLabel\":\"Password Change to\"}},{\"id\":\"3\",\"enabled\":true,\"type\":\"terms\",\"schema\":\"bucket\",\"params\":{\"field\":\"winlog.event_data.SubjectUserName\",\"orderBy\":\"1\",\"order\":\"desc\",\"size\":5,\"otherBucket\":false,\"otherBucketLabel\":\"Other\",\"missingBucket\":true,\"missingBucketLabel\":\"Missing\",\"customLabel\":\"Performed by\"}},{\"id\":\"4\",\"enabled\":true,\"type\":\"terms\",\"schema\":\"bucket\",\"params\":{\"field\":\"winlog.logon.id\",\"orderBy\":\"1\",\"order\":\"desc\",\"size\":5,\"otherBucket\":false,\"otherBucketLabel\":\"Other\",\"missingBucket\":false,\"missingBucketLabel\":\"Missing\",\"customLabel\":\"Performer LogonId\"}}]}"
      },
      "id": "da5ffe40-bcd9-11e9-b6a2-c9b4015c4baf",
      "migrationVersion": {
        "visualization": "7.3.1"
      },
      "references": [
        {
          "id": "winlogbeat-*",
          "name": "kibanaSavedObjectMeta.searchSourceJSON.index",
          "type": "index-pattern"
        },
        {
          "id": "winlogbeat-*",
          "name": "kibanaSavedObjectMeta.searchSourceJSON.filter[0].meta.index",
          "type": "index-pattern"
        }
      ],
      "type": "visualization",
      "updated_at": "2019-11-04T15:21:59.683Z",
      "version": "WzUxMSwxXQ=="
    },
    {
      "attributes": {
        "description": "",
        "kibanaSavedObjectMeta": {
          "searchSourceJSON": "{\"query\":{\"query\":\"\",\"language\":\"kuery\"},\"filter\":[{\"meta\":{\"alias\":null,\"negate\":false,\"type\":\"phrase\",\"key\":\"event.code\",\"value\":\"4767\",\"params\":{\"query\":\"4767\"},\"disabled\":false,\"indexRefName\":\"kibanaSavedObjectMeta.searchSourceJSON.filter[0].meta.index\"},\"query\":{\"match\":{\"event.code\":{\"query\":\"4767\",\"type\":\"phrase\"}}},\"$state\":{\"store\":\"appState\"}}],\"indexRefName\":\"kibanaSavedObjectMeta.searchSourceJSON.index\"}"
        },
        "title": "Unlocked Users - Table",
        "uiStateJSON": "{\"vis\":{\"params\":{\"sort\":{\"columnIndex\":null,\"direction\":null}}}}",
        "version": 1,
        "visState": "{\"title\":\"Unlocked Users - Table\",\"type\":\"table\",\"params\":{\"perPage\":10,\"showPartialRows\":false,\"showMetricsAtAllLevels\":false,\"sort\":{\"columnIndex\":null,\"direction\":null},\"showTotal\":false,\"totalFunc\":\"sum\",\"dimensions\":{\"metrics\":[{\"accessor\":3,\"format\":{\"id\":\"number\"},\"params\":{},\"aggType\":\"count\"}],\"buckets\":[{\"accessor\":0,\"format\":{\"id\":\"terms\",\"params\":{\"id\":\"string\",\"otherBucketLabel\":\"Other\",\"missingBucketLabel\":\"Missing\"}},\"params\":{},\"aggType\":\"terms\"},{\"accessor\":1,\"format\":{\"id\":\"terms\",\"params\":{\"id\":\"string\",\"otherBucketLabel\":\"Other\",\"missingBucketLabel\":\"Missing\"}},\"params\":{},\"aggType\":\"terms\"},{\"accessor\":2,\"format\":{\"id\":\"terms\",\"params\":{\"id\":\"string\",\"otherBucketLabel\":\"Other\",\"missingBucketLabel\":\"Missing\"}},\"params\":{},\"aggType\":\"terms\"}]}},\"aggs\":[{\"id\":\"1\",\"enabled\":true,\"type\":\"count\",\"schema\":\"metric\",\"params\":{}},{\"id\":\"2\",\"enabled\":true,\"type\":\"terms\",\"schema\":\"bucket\",\"params\":{\"field\":\"user.name\",\"orderBy\":\"1\",\"order\":\"desc\",\"size\":100,\"otherBucket\":false,\"otherBucketLabel\":\"Other\",\"missingBucket\":false,\"missingBucketLabel\":\"Missing\",\"customLabel\":\"Unlocked User\"}},{\"id\":\"3\",\"enabled\":true,\"type\":\"terms\",\"schema\":\"bucket\",\"params\":{\"field\":\"winlog.event_data.SubjectUserName\",\"orderBy\":\"1\",\"order\":\"desc\",\"size\":5,\"otherBucket\":false,\"otherBucketLabel\":\"Other\",\"missingBucket\":true,\"missingBucketLabel\":\"Missing\",\"customLabel\":\"Performed by\"}},{\"id\":\"4\",\"enabled\":true,\"type\":\"terms\",\"schema\":\"bucket\",\"params\":{\"field\":\"winlog.logon.id\",\"orderBy\":\"1\",\"order\":\"desc\",\"size\":5,\"otherBucket\":false,\"otherBucketLabel\":\"Other\",\"missingBucket\":false,\"missingBucketLabel\":\"Missing\",\"customLabel\":\"Performer Logonid\"}}]}"
      },
      "id": "da2110c0-bcea-11e9-b6a2-c9b4015c4baf",
      "migrationVersion": {
        "visualization": "7.3.1"
      },
      "references": [
        {
          "id": "winlogbeat-*",
          "name": "kibanaSavedObjectMeta.searchSourceJSON.index",
          "type": "index-pattern"
        },
        {
          "id": "winlogbeat-*",
          "name": "kibanaSavedObjectMeta.searchSourceJSON.filter[0].meta.index",
          "type": "index-pattern"
        }
      ],
      "type": "visualization",
      "updated_at": "2019-11-04T15:25:13.281Z",
      "version": "WzUxNSwxXQ=="
    },
    {
      "attributes": {
        "description": "",
        "kibanaSavedObjectMeta": {
          "searchSourceJSON": "{\"query\":{\"query\":\"\",\"language\":\"kuery\"},\"filter\":[{\"meta\":{\"alias\":null,\"negate\":false,\"type\":\"phrase\",\"key\":\"event.code\",\"value\":\"4738\",\"params\":{\"query\":\"4738\"},\"disabled\":false,\"indexRefName\":\"kibanaSavedObjectMeta.searchSourceJSON.filter[0].meta.index\"},\"query\":{\"match\":{\"event.code\":{\"query\":\"4738\",\"type\":\"phrase\"}}},\"$state\":{\"store\":\"appState\"}}],\"indexRefName\":\"kibanaSavedObjectMeta.searchSourceJSON.index\"}"
        },
        "title": "Users Changes  Table",
        "uiStateJSON": "{\"vis\":{\"params\":{\"sort\":{\"columnIndex\":null,\"direction\":null}}}}",
        "version": 1,
        "visState": "{\"title\":\"Users Changes  Table\",\"type\":\"table\",\"params\":{\"perPage\":10,\"showPartialRows\":false,\"showMetricsAtAllLevels\":false,\"sort\":{\"columnIndex\":null,\"direction\":null},\"showTotal\":false,\"totalFunc\":\"sum\",\"dimensions\":{\"metrics\":[{\"accessor\":3,\"format\":{\"id\":\"number\"},\"params\":{},\"aggType\":\"count\"}],\"buckets\":[{\"accessor\":0,\"format\":{\"id\":\"terms\",\"params\":{\"id\":\"string\",\"otherBucketLabel\":\"Other\",\"missingBucketLabel\":\"Missing\"}},\"params\":{},\"aggType\":\"terms\"},{\"accessor\":1,\"format\":{\"id\":\"terms\",\"params\":{\"id\":\"string\",\"otherBucketLabel\":\"Other\",\"missingBucketLabel\":\"Missing\"}},\"params\":{},\"aggType\":\"terms\"},{\"accessor\":2,\"format\":{\"id\":\"terms\",\"params\":{\"id\":\"string\",\"otherBucketLabel\":\"Other\",\"missingBucketLabel\":\"Missing\"}},\"params\":{},\"aggType\":\"terms\"}]}},\"aggs\":[{\"id\":\"1\",\"enabled\":true,\"type\":\"count\",\"schema\":\"metric\",\"params\":{}},{\"id\":\"2\",\"enabled\":true,\"type\":\"terms\",\"schema\":\"bucket\",\"params\":{\"field\":\"user.name\",\"orderBy\":\"1\",\"order\":\"desc\",\"size\":100,\"otherBucket\":false,\"otherBucketLabel\":\"Other\",\"missingBucket\":false,\"missingBucketLabel\":\"Missing\",\"customLabel\":\"Changed  User\"}},{\"id\":\"3\",\"enabled\":true,\"type\":\"terms\",\"schema\":\"bucket\",\"params\":{\"field\":\"winlog.event_data.SubjectUserName\",\"orderBy\":\"1\",\"order\":\"desc\",\"size\":5,\"otherBucket\":false,\"otherBucketLabel\":\"Other\",\"missingBucket\":true,\"missingBucketLabel\":\"Missing\",\"customLabel\":\"Performed by\"}},{\"id\":\"4\",\"enabled\":true,\"type\":\"terms\",\"schema\":\"bucket\",\"params\":{\"field\":\"winlog.logon.id\",\"orderBy\":\"1\",\"order\":\"desc\",\"size\":5,\"otherBucket\":false,\"otherBucketLabel\":\"Other\",\"missingBucket\":false,\"missingBucketLabel\":\"Missing\",\"customLabel\":\"Performer LogonId\"}}]}"
      },
      "id": "abf96c10-bcea-11e9-b6a2-c9b4015c4baf",
      "migrationVersion": {
        "visualization": "7.3.1"
      },
      "references": [
        {
          "id": "winlogbeat-*",
          "name": "kibanaSavedObjectMeta.searchSourceJSON.index",
          "type": "index-pattern"
        },
        {
          "id": "winlogbeat-*",
          "name": "kibanaSavedObjectMeta.searchSourceJSON.filter[0].meta.index",
          "type": "index-pattern"
        }
      ],
      "type": "visualization",
      "updated_at": "2019-11-04T15:26:15.729Z",
      "version": "WzUxNiwxXQ=="
    },
    {
      "attributes": {
        "description": "",
        "kibanaSavedObjectMeta": {
          "searchSourceJSON": "{\"query\":{\"query\":\"\",\"language\":\"kuery\"},\"filter\":[{\"meta\":{\"alias\":null,\"negate\":false,\"type\":\"phrase\",\"key\":\"event.code\",\"value\":\"4740\",\"params\":{\"query\":\"4740\"},\"disabled\":false,\"indexRefName\":\"kibanaSavedObjectMeta.searchSourceJSON.filter[0].meta.index\"},\"query\":{\"match\":{\"event.code\":{\"query\":\"4740\",\"type\":\"phrase\"}}},\"$state\":{\"store\":\"appState\"}}],\"indexRefName\":\"kibanaSavedObjectMeta.searchSourceJSON.index\"}"
        },
        "title": "Users Locked Out - Table",
        "uiStateJSON": "{\"vis\":{\"params\":{\"sort\":{\"columnIndex\":null,\"direction\":null}}}}",
        "version": 1,
        "visState": "{\"title\":\"Users Locked Out - Table\",\"type\":\"table\",\"params\":{\"perPage\":10,\"showPartialRows\":false,\"showMetricsAtAllLevels\":false,\"sort\":{\"columnIndex\":null,\"direction\":null},\"showTotal\":false,\"totalFunc\":\"sum\",\"dimensions\":{\"metrics\":[{\"accessor\":3,\"format\":{\"id\":\"number\"},\"params\":{},\"aggType\":\"count\"}],\"buckets\":[{\"accessor\":0,\"format\":{\"id\":\"terms\",\"params\":{\"id\":\"string\",\"otherBucketLabel\":\"Other\",\"missingBucketLabel\":\"Missing\"}},\"params\":{},\"aggType\":\"terms\"},{\"accessor\":1,\"format\":{\"id\":\"terms\",\"params\":{\"id\":\"string\",\"otherBucketLabel\":\"Other\",\"missingBucketLabel\":\"Missing\"}},\"params\":{},\"aggType\":\"terms\"},{\"accessor\":2,\"format\":{\"id\":\"terms\",\"params\":{\"id\":\"string\",\"otherBucketLabel\":\"Other\",\"missingBucketLabel\":\"Missing\"}},\"params\":{},\"aggType\":\"terms\"}]}},\"aggs\":[{\"id\":\"1\",\"enabled\":true,\"type\":\"count\",\"schema\":\"metric\",\"params\":{}},{\"id\":\"2\",\"enabled\":true,\"type\":\"terms\",\"schema\":\"bucket\",\"params\":{\"field\":\"user.name\",\"orderBy\":\"1\",\"order\":\"desc\",\"size\":100,\"otherBucket\":false,\"otherBucketLabel\":\"Other\",\"missingBucket\":false,\"missingBucketLabel\":\"Missing\",\"customLabel\":\"Locked  User\"}},{\"id\":\"3\",\"enabled\":true,\"type\":\"terms\",\"schema\":\"bucket\",\"params\":{\"field\":\"winlog.event_data.SubjectUserName\",\"orderBy\":\"1\",\"order\":\"desc\",\"size\":5,\"otherBucket\":false,\"otherBucketLabel\":\"Other\",\"missingBucket\":true,\"missingBucketLabel\":\"Missing\",\"customLabel\":\"Performed by\"}},{\"id\":\"4\",\"enabled\":true,\"type\":\"terms\",\"schema\":\"bucket\",\"params\":{\"field\":\"winlog.logon.id\",\"orderBy\":\"1\",\"order\":\"desc\",\"size\":5,\"otherBucket\":false,\"otherBucketLabel\":\"Other\",\"missingBucket\":false,\"missingBucketLabel\":\"Missing\",\"customLabel\":\"Performer LogonId\"}}]}"
      },
      "id": "4ac8f5f0-bcfe-11e9-b6a2-c9b4015c4baf",
      "migrationVersion": {
        "visualization": "7.3.1"
      },
      "references": [
        {
          "id": "winlogbeat-*",
          "name": "kibanaSavedObjectMeta.searchSourceJSON.index",
          "type": "index-pattern"
        },
        {
          "id": "winlogbeat-*",
          "name": "kibanaSavedObjectMeta.searchSourceJSON.filter[0].meta.index",
          "type": "index-pattern"
        }
      ],
      "type": "visualization",
      "updated_at": "2019-11-04T15:24:32.268Z",
      "version": "WzUxNCwxXQ=="
    },
    {
      "attributes": {
        "description": "",
        "kibanaSavedObjectMeta": {
          "searchSourceJSON": "{\"query\":{\"query\":\"\",\"language\":\"kuery\"},\"filter\":[{\"meta\":{\"type\":\"phrases\",\"key\":\"event.code\",\"value\":\"4720, 4722, 4723, 4724, 4725, 4726, 4738, 4740, 4767, 4781, 4798\",\"params\":[\"4720\",\"4722\",\"4723\",\"4724\",\"4725\",\"4726\",\"4738\",\"4740\",\"4767\",\"4781\",\"4798\"],\"alias\":null,\"negate\":false,\"disabled\":false,\"indexRefName\":\"kibanaSavedObjectMeta.searchSourceJSON.filter[0].meta.index\"},\"query\":{\"bool\":{\"should\":[{\"match_phrase\":{\"event.code\":\"4720\"}},{\"match_phrase\":{\"event.code\":\"4722\"}},{\"match_phrase\":{\"event.code\":\"4723\"}},{\"match_phrase\":{\"event.code\":\"4724\"}},{\"match_phrase\":{\"event.code\":\"4725\"}},{\"match_phrase\":{\"event.code\":\"4726\"}},{\"match_phrase\":{\"event.code\":\"4738\"}},{\"match_phrase\":{\"event.code\":\"4740\"}},{\"match_phrase\":{\"event.code\":\"4767\"}},{\"match_phrase\":{\"event.code\":\"4781\"}},{\"match_phrase\":{\"event.code\":\"4798\"}}],\"minimum_should_match\":1}},\"$state\":{\"store\":\"appState\"}}],\"indexRefName\":\"kibanaSavedObjectMeta.searchSourceJSON.index\"}"
        },
        "title": "4_Event_Distribution in time",
        "uiStateJSON": "{}",
        "version": 1,
        "visState": "{\"title\":\"4_Event_Distribution in time\",\"type\":\"histogram\",\"params\":{\"type\":\"histogram\",\"grid\":{\"categoryLines\":false},\"categoryAxes\":[{\"id\":\"CategoryAxis-1\",\"type\":\"category\",\"position\":\"bottom\",\"show\":true,\"style\":{},\"scale\":{\"type\":\"linear\"},\"labels\":{\"show\":true,\"filter\":true,\"truncate\":100},\"title\":{}}],\"valueAxes\":[{\"id\":\"ValueAxis-1\",\"name\":\"LeftAxis-1\",\"type\":\"value\",\"position\":\"left\",\"show\":true,\"style\":{},\"scale\":{\"type\":\"linear\",\"mode\":\"normal\"},\"labels\":{\"show\":true,\"rotate\":0,\"filter\":false,\"truncate\":100},\"title\":{\"text\":\"Count\"}}],\"seriesParams\":[{\"show\":\"true\",\"type\":\"histogram\",\"mode\":\"stacked\",\"data\":{\"label\":\"Count\",\"id\":\"1\"},\"valueAxis\":\"ValueAxis-1\",\"drawLinesBetweenPoints\":true,\"showCircles\":true}],\"addTooltip\":true,\"addLegend\":true,\"legendPosition\":\"bottom\",\"times\":[],\"addTimeMarker\":false,\"labels\":{\"show\":true},\"dimensions\":{\"x\":{\"accessor\":0,\"format\":{\"id\":\"date\",\"params\":{\"pattern\":\"YYYY-MM-DD HH:mm\"}},\"params\":{\"date\":true,\"interval\":\"PT12H\",\"format\":\"YYYY-MM-DD HH:mm\",\"bounds\":{\"min\":\"2019-09-20T13:10:39.628Z\",\"max\":\"2019-11-04T14:10:39.628Z\"}},\"aggType\":\"date_histogram\"},\"y\":[{\"accessor\":2,\"format\":{\"id\":\"number\"},\"params\":{},\"aggType\":\"count\"}],\"series\":[{\"accessor\":1,\"format\":{},\"params\":{},\"aggType\":\"filters\"}]}},\"aggs\":[{\"id\":\"1\",\"enabled\":true,\"type\":\"count\",\"schema\":\"metric\",\"params\":{}},{\"id\":\"2\",\"enabled\":true,\"type\":\"date_histogram\",\"schema\":\"segment\",\"params\":{\"field\":\"@timestamp\",\"timeRange\":{\"from\":\"now-45d\",\"to\":\"now\"},\"useNormalizedEsInterval\":true,\"interval\":\"auto\",\"drop_partials\":false,\"min_doc_count\":1,\"extended_bounds\":{}}},{\"id\":\"3\",\"enabled\":true,\"type\":\"terms\",\"schema\":\"group\",\"params\":{\"field\":\"event.action\",\"orderBy\":\"1\",\"order\":\"desc\",\"size\":5,\"otherBucket\":false,\"otherBucketLabel\":\"Other\",\"missingBucket\":false,\"missingBucketLabel\":\"Missing\"}}]}"
      },
      "id": "8f723a10-bd97-11e9-b9c5-fddc96658612",
      "migrationVersion": {
        "visualization": "7.3.1"
      },
      "references": [
        {
          "id": "winlogbeat-*",
          "name": "kibanaSavedObjectMeta.searchSourceJSON.index",
          "type": "index-pattern"
        },
        {
          "id": "winlogbeat-*",
          "name": "kibanaSavedObjectMeta.searchSourceJSON.filter[0].meta.index",
          "type": "index-pattern"
        }
      ],
      "type": "visualization",
      "updated_at": "2019-11-04T14:12:00.548Z",
      "version": "WzQ3NiwxXQ=="
    },
    {
      "attributes": {
        "columns": [
          "user.name",
          "source.domain",
          "source.ip",
          "winlog.logon.id",
          "winlog.logon.type"
        ],
        "description": "",
        "hits": 0,
        "kibanaSavedObjectMeta": {
          "searchSourceJSON": "{\"highlightAll\":true,\"version\":true,\"query\":{\"query\":\"\",\"language\":\"kuery\"},\"filter\":[{\"meta\":{\"type\":\"phrases\",\"key\":\"event.code\",\"value\":\"4624\",\"params\":[\"4624\"],\"alias\":null,\"negate\":false,\"disabled\":false,\"indexRefName\":\"kibanaSavedObjectMeta.searchSourceJSON.filter[0].meta.index\"},\"query\":{\"bool\":{\"should\":[{\"match_phrase\":{\"event.code\":\"4624\"}}],\"minimum_should_match\":1}},\"$state\":{\"store\":\"appState\"}}],\"indexRefName\":\"kibanaSavedObjectMeta.searchSourceJSON.index\"}"
        },
        "sort": [
          "@timestamp",
          "desc"
        ],
        "title": "Logon Details",
        "version": 1
      },
      "id": "7e178c80-fee1-11e9-8405-516218e3d268",
      "migrationVersion": {
        "search": "7.0.0"
      },
      "references": [
        {
          "id": "winlogbeat-*",
          "name": "kibanaSavedObjectMeta.searchSourceJSON.index",
          "type": "index-pattern"
        },
        {
          "id": "winlogbeat-*",
          "name": "kibanaSavedObjectMeta.searchSourceJSON.filter[0].meta.index",
          "type": "index-pattern"
        }
      ],
      "type": "search",
      "updated_at": "2019-11-04T09:00:36.878Z",
      "version": "WzM2MiwxXQ=="
    },
    {
      "attributes": {
        "columns": [
          "event.action",
          "user.name",
          "user.domain",
          "winlog.event_data.SubjectUserName",
          "winlog.event_data.SubjectDomainName",
          "winlog.logon.id"
        ],
        "description": "",
        "hits": 0,
        "kibanaSavedObjectMeta": {
          "searchSourceJSON": "{\"highlightAll\":true,\"version\":true,\"query\":{\"query\":\"\",\"language\":\"lucene\"},\"filter\":[{\"meta\":{\"type\":\"phrases\",\"key\":\"event.code\",\"value\":\"4720, 4722, 4723, 4724, 4725, 4726, 4738, 4740, 4767, 4781\",\"params\":[\"4720\",\"4722\",\"4723\",\"4724\",\"4725\",\"4726\",\"4738\",\"4740\",\"4767\",\"4781\"],\"alias\":null,\"negate\":false,\"disabled\":false,\"indexRefName\":\"kibanaSavedObjectMeta.searchSourceJSON.filter[0].meta.index\"},\"query\":{\"bool\":{\"should\":[{\"match_phrase\":{\"event.code\":\"4720\"}},{\"match_phrase\":{\"event.code\":\"4722\"}},{\"match_phrase\":{\"event.code\":\"4723\"}},{\"match_phrase\":{\"event.code\":\"4724\"}},{\"match_phrase\":{\"event.code\":\"4725\"}},{\"match_phrase\":{\"event.code\":\"4726\"}},{\"match_phrase\":{\"event.code\":\"4738\"}},{\"match_phrase\":{\"event.code\":\"4740\"}},{\"match_phrase\":{\"event.code\":\"4767\"}},{\"match_phrase\":{\"event.code\":\"4781\"}}],\"minimum_should_match\":1}},\"$state\":{\"store\":\"appState\"}}],\"indexRefName\":\"kibanaSavedObjectMeta.searchSourceJSON.index\"}"
        },
        "sort": [
          "@timestamp",
          "desc"
        ],
        "title": "User management Details - Search",
        "version": 1
      },
      "id": "324686c0-fefb-11e9-8405-516218e3d268",
      "migrationVersion": {
        "search": "7.0.0"
      },
      "references": [
        {
          "id": "winlogbeat-*",
          "name": "kibanaSavedObjectMeta.searchSourceJSON.index",
          "type": "index-pattern"
        },
        {
          "id": "winlogbeat-*",
          "name": "kibanaSavedObjectMeta.searchSourceJSON.filter[0].meta.index",
          "type": "index-pattern"
        }
      ],
      "type": "search",
      "updated_at": "2019-11-04T12:04:57.352Z",
      "version": "WzQ3NSwxXQ=="
    },
    {
      "attributes": {
        "description": "",
        "kibanaSavedObjectMeta": {
          "searchSourceJSON": "{\"query\":{\"query\":\"\",\"language\":\"lucene\"},\"filter\":[]}"
        },
        "title": "Users Disabled - VB Metric",
        "uiStateJSON": "{}",
        "version": 1,
        "visState": "{\"title\":\"Users Disabled - VB Metric\",\"type\":\"metrics\",\"params\":{\"id\":\"61ca57f0-469d-11e7-af02-69e470af7417\",\"type\":\"metric\",\"series\":[{\"id\":\"61ca57f1-469d-11e7-af02-69e470af7417\",\"color\":\"#68BC00\",\"split_mode\":\"everything\",\"metrics\":[{\"id\":\"61ca57f2-469d-11e7-af02-69e470af7417\",\"type\":\"count\"}],\"separate_axis\":0,\"axis_position\":\"right\",\"formatter\":\"number\",\"chart_type\":\"line\",\"line_width\":1,\"point_size\":1,\"fill\":0.5,\"stacked\":\"none\",\"label\":\"Users Disabled\"}],\"time_field\":\"\",\"index_pattern\":\"\",\"interval\":\"90d\",\"axis_position\":\"left\",\"axis_formatter\":\"number\",\"axis_scale\":\"normal\",\"show_legend\":1,\"show_grid\":1,\"default_index_pattern\":\"winlogbeat-*\",\"default_timefield\":\"@timestamp\",\"background_color_rules\":[{\"value\":0,\"id\":\"8d597960-ff18-11e9-8249-2371c695f3b0\",\"operator\":\"lte\"},{\"value\":1,\"id\":\"a3f59730-ff18-11e9-8249-2371c695f3b0\",\"operator\":\"gte\",\"background_color\":\"rgba(219,223,0,1)\"}],\"filter\":{\"query\":\"event.code: \\\"4725\\\" \",\"language\":\"kuery\"},\"drop_last_bucket\":0},\"aggs\":[]}"
      },
      "id": "97c70300-ff1c-11e9-8405-516218e3d268",
      "migrationVersion": {
        "visualization": "7.3.1"
      },
      "references": [],
      "type": "visualization",
      "updated_at": "2019-11-04T16:06:23.209Z",
      "version": "WzUyOSwxXQ=="
    },
    {
      "attributes": {
        "description": "",
        "kibanaSavedObjectMeta": {
          "searchSourceJSON": "{\"query\":{\"query\":\"\",\"language\":\"lucene\"},\"filter\":[]}"
        },
        "title": "Users Enabled - VB Metric",
        "uiStateJSON": "{}",
        "version": 1,
        "visState": "{\"title\":\"Users Enabled - VB Metric\",\"type\":\"metrics\",\"params\":{\"id\":\"61ca57f0-469d-11e7-af02-69e470af7417\",\"type\":\"metric\",\"series\":[{\"id\":\"61ca57f1-469d-11e7-af02-69e470af7417\",\"color\":\"#68BC00\",\"split_mode\":\"everything\",\"metrics\":[{\"id\":\"61ca57f2-469d-11e7-af02-69e470af7417\",\"type\":\"count\"}],\"separate_axis\":0,\"axis_position\":\"right\",\"formatter\":\"number\",\"chart_type\":\"line\",\"line_width\":1,\"point_size\":1,\"fill\":0.5,\"stacked\":\"none\",\"label\":\"Users Enabled\"}],\"time_field\":\"\",\"index_pattern\":\"\",\"interval\":\"90d\",\"axis_position\":\"left\",\"axis_formatter\":\"number\",\"axis_scale\":\"normal\",\"show_legend\":1,\"show_grid\":1,\"default_index_pattern\":\"winlogbeat-*\",\"default_timefield\":\"@timestamp\",\"background_color_rules\":[{\"value\":0,\"id\":\"8d597960-ff18-11e9-8249-2371c695f3b0\",\"operator\":\"lte\"},{\"value\":1,\"id\":\"a3f59730-ff18-11e9-8249-2371c695f3b0\",\"operator\":\"gte\",\"background_color\":\"rgba(251,158,0,1)\"}],\"filter\":{\"query\":\"event.code: \\\"4722\\\" \",\"language\":\"kuery\"},\"drop_last_bucket\":0},\"aggs\":[]}"
      },
      "id": "bf45dc50-ff1a-11e9-8405-516218e3d268",
      "migrationVersion": {
        "visualization": "7.3.1"
      },
      "references": [],
      "type": "visualization",
      "updated_at": "2019-11-04T16:01:43.218Z",
      "version": "WzUyNCwxXQ=="
    },
    {
      "attributes": {
        "description": "",
        "kibanaSavedObjectMeta": {
          "searchSourceJSON": "{\"query\":{\"query\":\"\",\"language\":\"lucene\"},\"filter\":[]}"
        },
        "title": "Users Deleted - VB Metric",
        "uiStateJSON": "{}",
        "version": 1,
        "visState": "{\"title\":\"Users Deleted - VB Metric\",\"type\":\"metrics\",\"params\":{\"id\":\"61ca57f0-469d-11e7-af02-69e470af7417\",\"type\":\"metric\",\"series\":[{\"id\":\"61ca57f1-469d-11e7-af02-69e470af7417\",\"color\":\"#68BC00\",\"split_mode\":\"everything\",\"metrics\":[{\"id\":\"61ca57f2-469d-11e7-af02-69e470af7417\",\"type\":\"count\"}],\"separate_axis\":0,\"axis_position\":\"right\",\"formatter\":\"number\",\"chart_type\":\"line\",\"line_width\":1,\"point_size\":1,\"fill\":0.5,\"stacked\":\"none\",\"label\":\"Users Deleted\"}],\"time_field\":\"\",\"index_pattern\":\"\",\"interval\":\"90d\",\"axis_position\":\"left\",\"axis_formatter\":\"number\",\"axis_scale\":\"normal\",\"show_legend\":1,\"show_grid\":1,\"default_index_pattern\":\"winlogbeat-*\",\"default_timefield\":\"@timestamp\",\"background_color_rules\":[{\"value\":0,\"id\":\"8d597960-ff18-11e9-8249-2371c695f3b0\",\"operator\":\"lte\"},{\"value\":1,\"id\":\"a3f59730-ff18-11e9-8249-2371c695f3b0\",\"operator\":\"gte\",\"background_color\":\"rgba(176,188,0,1)\"}],\"filter\":{\"query\":\"event.code: \\\"4726\\\" \",\"language\":\"kuery\"},\"drop_last_bucket\":0},\"aggs\":[]}"
      },
      "id": "7322f9f0-ff1c-11e9-8405-516218e3d268",
      "migrationVersion": {
        "visualization": "7.3.1"
      },
      "references": [],
      "type": "visualization",
      "updated_at": "2019-11-04T16:02:50.506Z",
      "version": "WzUyNiwxXQ=="
    },
    {
      "attributes": {
        "description": "",
        "kibanaSavedObjectMeta": {
          "searchSourceJSON": "{\"query\":{\"query\":\"\",\"language\":\"lucene\"},\"filter\":[]}"
        },
        "title": "Users Created - VB Metric",
        "uiStateJSON": "{}",
        "version": 1,
        "visState": "{\"title\":\"Users Created - VB Metric\",\"type\":\"metrics\",\"params\":{\"id\":\"61ca57f0-469d-11e7-af02-69e470af7417\",\"type\":\"metric\",\"series\":[{\"id\":\"61ca57f1-469d-11e7-af02-69e470af7417\",\"color\":\"#68BC00\",\"split_mode\":\"everything\",\"metrics\":[{\"id\":\"61ca57f2-469d-11e7-af02-69e470af7417\",\"type\":\"count\"}],\"separate_axis\":0,\"axis_position\":\"right\",\"formatter\":\"number\",\"chart_type\":\"line\",\"line_width\":1,\"point_size\":1,\"fill\":0.5,\"stacked\":\"none\",\"label\":\"Users Created\"}],\"time_field\":\"\",\"index_pattern\":\"\",\"interval\":\"90d\",\"axis_position\":\"left\",\"axis_formatter\":\"number\",\"axis_scale\":\"normal\",\"show_legend\":1,\"show_grid\":1,\"default_index_pattern\":\"winlogbeat-*\",\"default_timefield\":\"@timestamp\",\"background_color_rules\":[{\"value\":0,\"id\":\"8d597960-ff18-11e9-8249-2371c695f3b0\",\"operator\":\"lte\"},{\"value\":1,\"id\":\"a3f59730-ff18-11e9-8249-2371c695f3b0\",\"operator\":\"gte\",\"background_color\":\"rgba(159,5,0,1)\"}],\"filter\":{\"query\":\"event.code: \\\"4720\\\" \",\"language\":\"kuery\"},\"drop_last_bucket\":0},\"aggs\":[]}"
      },
      "id": "d3a5fec0-ff18-11e9-8405-516218e3d268",
      "migrationVersion": {
        "visualization": "7.3.1"
      },
      "references": [],
      "type": "visualization",
      "updated_at": "2019-11-04T15:49:13.249Z",
      "version": "WzUyMiwxXQ=="
    },
    {
      "attributes": {
        "description": "",
        "kibanaSavedObjectMeta": {
          "searchSourceJSON": "{\"query\":{\"query\":\"\",\"language\":\"lucene\"},\"filter\":[]}"
        },
        "title": "Users Unlocks - VB Metric",
        "uiStateJSON": "{}",
        "version": 1,
        "visState": "{\"title\":\"Users Unlocks - VB Metric\",\"type\":\"metrics\",\"params\":{\"id\":\"61ca57f0-469d-11e7-af02-69e470af7417\",\"type\":\"metric\",\"series\":[{\"id\":\"61ca57f1-469d-11e7-af02-69e470af7417\",\"color\":\"#68BC00\",\"split_mode\":\"everything\",\"metrics\":[{\"id\":\"61ca57f2-469d-11e7-af02-69e470af7417\",\"type\":\"count\"}],\"separate_axis\":0,\"axis_position\":\"right\",\"formatter\":\"number\",\"chart_type\":\"line\",\"line_width\":1,\"point_size\":1,\"fill\":0.5,\"stacked\":\"none\",\"label\":\"Users Unlocks\"}],\"time_field\":\"\",\"index_pattern\":\"\",\"interval\":\"90d\",\"axis_position\":\"left\",\"axis_formatter\":\"number\",\"axis_scale\":\"normal\",\"show_legend\":1,\"show_grid\":1,\"default_index_pattern\":\"winlogbeat-*\",\"default_timefield\":\"@timestamp\",\"background_color_rules\":[{\"value\":0,\"id\":\"8d597960-ff18-11e9-8249-2371c695f3b0\",\"operator\":\"lte\"},{\"value\":1,\"id\":\"a3f59730-ff18-11e9-8249-2371c695f3b0\",\"operator\":\"gte\",\"background_color\":\"rgba(254,146,0,1)\"}],\"filter\":{\"query\":\"event.code: \\\"4767\\\" \",\"language\":\"kuery\"},\"drop_last_bucket\":0},\"aggs\":[]}"
      },
      "id": "1b6725f0-ff1d-11e9-8405-516218e3d268",
      "migrationVersion": {
        "visualization": "7.3.1"
      },
      "references": [],
      "type": "visualization",
      "updated_at": "2019-11-04T16:08:21.249Z",
      "version": "WzUzMiwxXQ=="
    },
    {
      "attributes": {
        "description": "",
        "kibanaSavedObjectMeta": {
          "searchSourceJSON": "{\"query\":{\"query\":\"\",\"language\":\"lucene\"},\"filter\":[]}"
        },
        "title": "Users Password Changes - VB Metric",
        "uiStateJSON": "{}",
        "version": 1,
        "visState": "{\"title\":\"Users Password Changes - VB Metric\",\"type\":\"metrics\",\"params\":{\"id\":\"61ca57f0-469d-11e7-af02-69e470af7417\",\"type\":\"metric\",\"series\":[{\"id\":\"61ca57f1-469d-11e7-af02-69e470af7417\",\"color\":\"#68BC00\",\"split_mode\":\"everything\",\"metrics\":[{\"id\":\"61ca57f2-469d-11e7-af02-69e470af7417\",\"type\":\"count\"}],\"separate_axis\":0,\"axis_position\":\"right\",\"formatter\":\"number\",\"chart_type\":\"line\",\"line_width\":1,\"point_size\":1,\"fill\":0.5,\"stacked\":\"none\",\"label\":\"Password Changes/Reset\"}],\"time_field\":\"\",\"index_pattern\":\"\",\"interval\":\"90d\",\"axis_position\":\"left\",\"axis_formatter\":\"number\",\"axis_scale\":\"normal\",\"show_legend\":1,\"show_grid\":1,\"default_index_pattern\":\"winlogbeat-*\",\"default_timefield\":\"@timestamp\",\"background_color_rules\":[{\"value\":0,\"id\":\"8d597960-ff18-11e9-8249-2371c695f3b0\",\"operator\":\"lte\"},{\"value\":1,\"id\":\"a3f59730-ff18-11e9-8249-2371c695f3b0\",\"operator\":\"gte\",\"background_color\":\"rgba(22,165,165,1)\"}],\"filter\":{\"query\":\"event.code: \\\"4723\\\"  OR event.code: \\\"4724\\\"\",\"language\":\"kuery\"},\"drop_last_bucket\":0},\"aggs\":[]}"
      },
      "id": "60301890-ff1d-11e9-8405-516218e3d268",
      "migrationVersion": {
        "visualization": "7.3.1"
      },
      "references": [],
      "type": "visualization",
      "updated_at": "2019-11-04T16:10:09.726Z",
      "version": "WzUzNCwxXQ=="
    },
    {
      "attributes": {
        "description": "",
        "kibanaSavedObjectMeta": {
          "searchSourceJSON": "{\"query\":{\"query\":\"\",\"language\":\"lucene\"},\"filter\":[]}"
        },
        "title": "Users locked Out - VB Metric",
        "uiStateJSON": "{}",
        "version": 1,
        "visState": "{\"title\":\"Users locked Out - VB Metric\",\"type\":\"metrics\",\"params\":{\"id\":\"61ca57f0-469d-11e7-af02-69e470af7417\",\"type\":\"metric\",\"series\":[{\"id\":\"61ca57f1-469d-11e7-af02-69e470af7417\",\"color\":\"#68BC00\",\"split_mode\":\"everything\",\"metrics\":[{\"id\":\"61ca57f2-469d-11e7-af02-69e470af7417\",\"type\":\"count\"}],\"separate_axis\":0,\"axis_position\":\"right\",\"formatter\":\"number\",\"chart_type\":\"line\",\"line_width\":1,\"point_size\":1,\"fill\":0.5,\"stacked\":\"none\",\"label\":\"Users Locked Out\"}],\"time_field\":\"\",\"index_pattern\":\"\",\"interval\":\"90d\",\"axis_position\":\"left\",\"axis_formatter\":\"number\",\"axis_scale\":\"normal\",\"show_legend\":1,\"show_grid\":1,\"default_index_pattern\":\"winlogbeat-*\",\"default_timefield\":\"@timestamp\",\"background_color_rules\":[{\"value\":0,\"id\":\"8d597960-ff18-11e9-8249-2371c695f3b0\",\"operator\":\"lte\"},{\"value\":1,\"id\":\"a3f59730-ff18-11e9-8249-2371c695f3b0\",\"operator\":\"gte\",\"background_color\":\"rgba(51,51,51,1)\"}],\"filter\":{\"query\":\"event.code: \\\"4740\\\"\",\"language\":\"kuery\"},\"drop_last_bucket\":0},\"aggs\":[]}"
      },
      "id": "9dd22440-ff1d-11e9-8405-516218e3d268",
      "migrationVersion": {
        "visualization": "7.3.1"
      },
      "references": [],
      "type": "visualization",
      "updated_at": "2019-11-04T16:24:47.051Z",
      "version": "WzU0MCwxXQ=="
    },
    {
      "attributes": {
        "description": "",
        "kibanaSavedObjectMeta": {
          "searchSourceJSON": "{\"query\":{\"query\":\"\",\"language\":\"lucene\"},\"filter\":[]}"
        },
        "title": "Users Changes  VB Metric",
        "uiStateJSON": "{}",
        "version": 1,
        "visState": "{\"title\":\"Users Changes  VB Metric\",\"type\":\"metrics\",\"params\":{\"id\":\"61ca57f0-469d-11e7-af02-69e470af7417\",\"type\":\"metric\",\"series\":[{\"id\":\"61ca57f1-469d-11e7-af02-69e470af7417\",\"color\":\"#68BC00\",\"split_mode\":\"everything\",\"metrics\":[{\"id\":\"61ca57f2-469d-11e7-af02-69e470af7417\",\"type\":\"count\"}],\"separate_axis\":0,\"axis_position\":\"right\",\"formatter\":\"number\",\"chart_type\":\"line\",\"line_width\":1,\"point_size\":1,\"fill\":0.5,\"stacked\":\"none\",\"label\":\"Users Changes\"}],\"time_field\":\"\",\"index_pattern\":\"\",\"interval\":\"90d\",\"axis_position\":\"left\",\"axis_formatter\":\"number\",\"axis_scale\":\"normal\",\"show_legend\":1,\"show_grid\":1,\"default_index_pattern\":\"winlogbeat-*\",\"default_timefield\":\"@timestamp\",\"background_color_rules\":[{\"value\":0,\"id\":\"8d597960-ff18-11e9-8249-2371c695f3b0\",\"operator\":\"lte\"},{\"value\":1,\"id\":\"a3f59730-ff18-11e9-8249-2371c695f3b0\",\"operator\":\"gte\",\"background_color\":\"rgba(179,179,179,1)\"}],\"filter\":{\"query\":\"event.code: \\\"4738\\\" \",\"language\":\"kuery\"},\"drop_last_bucket\":0},\"aggs\":[]}"
      },
      "id": "c9d959f0-ff1d-11e9-8405-516218e3d268",
      "migrationVersion": {
        "visualization": "7.3.1"
      },
      "references": [],
      "type": "visualization",
      "updated_at": "2019-11-04T16:12:34.736Z",
      "version": "WzUzOCwxXQ=="
    }
  ],
  "version": "7.3.1"
}
